{
    "Experiments": [
        {
            "Name": "experiment1",
            "Config": {
                "TracePath": "data/traces/example",
                "OutputPathPrefix": "data/out/experiment1/single",
                "ExperimentDuration": 1
            },
            "IatGeneration": false,
            "Generated": false,
            "Verbosity": "info",
            "TracesDir": "",
            "PreScriptPath": "",
            "PostScriptPath": ""
        },
        {
            "Name": "experiment2",
            "Config": {
                "ExperimentDuration": 1
            },
            "IatGeneration": false,
            "Generated": false,
            "Verbosity": "info",
            "TracesDir": "data/traces/multi-exp-test",
            "OutputDir": "data/out/multi-test",
            "PreScriptPath": "",
            "PostScriptPath": ""
        }      
    ],
    "PreScriptPath": "",
    "PostScriptPath": "",
    "BaseConfigPath": "cmd/multi_loader/base_loader_config.json"
}